README.txt
setup.py
cmsplugin_blog_search/__init__.py
cmsplugin_blog_search/search_indexes.py
cmsplugin_blog_search.egg-info/PKG-INFO
cmsplugin_blog_search.egg-info/SOURCES.txt
cmsplugin_blog_search.egg-info/dependency_links.txt
cmsplugin_blog_search.egg-info/requires.txt
cmsplugin_blog_search.egg-info/top_level.txt