Metadata-Version: 1.0
Name: cmsplugin-blog-search
Version: 0.9
Summary: Searching using language facets for cmsplugin-blog.
Home-page: http://github.com/fivethreeo/cmsplugin-blog-search/
Author: Oyvind Saltvik
Author-email: oyvind.saltvik@gmail.com
License: UNKNOWN
Platform: UNKNOWN
